flowws_analysis/Center.py
flowws_analysis/Colormap.py
flowws_analysis/Diffraction.py
flowws_analysis/GTAR.py
flowws_analysis/Garnett.py
flowws_analysis/Plato.py
flowws_analysis/Pyriodic.py
flowws_analysis/Save.py
flowws_analysis/SaveGarnett.py
flowws_analysis/Selection.py
flowws_analysis/ViewNotebook.py
flowws_analysis/ViewQt.py
flowws_analysis/__init__.py
flowws_analysis/_diffraction_primitive.py
flowws_analysis/version.py
flowws_analysis-0.7.0.dist-info/LICENSE
flowws_analysis-0.7.0.dist-info/METADATA
flowws_analysis-0.7.0.dist-info/WHEEL
flowws_analysis-0.7.0.dist-info/entry_points.txt
flowws_analysis-0.7.0.dist-info/top_level.txt
flowws_analysis-0.7.0.dist-info/RECORD
