Metadata-Version: 2.1
Name: flowws-analysis
Version: 0.7.0
Summary: Stage-based scientific workflows for system analysis
Home-page: UNKNOWN
Author: Matthew Spellings
Author-email: matthew.p.spellings@gmail.com
License: MIT
Platform: UNKNOWN
Classifier: Development Status :: 3 - Alpha
Classifier: License :: OSI Approved :: MIT License
Classifier: Programming Language :: Python :: 3
Requires-Python: >=3
Requires-Dist: flowws (>=0.4.0)
Provides-Extra: garnett
Requires-Dist: garnett ; extra == 'garnett'
Requires-Dist: gsd ; extra == 'garnett'
Requires-Dist: gtar ; extra == 'garnett'
Requires-Dist: pycifrw ; extra == 'garnett'
Provides-Extra: gtar
Requires-Dist: gtar ; extra == 'gtar'
Provides-Extra: notebook
Requires-Dist: ipython ; extra == 'notebook'
Requires-Dist: ipywidgets ; extra == 'notebook'
Provides-Extra: plato
Requires-Dist: plato-draw (>=1.11) ; extra == 'plato'
Requires-Dist: pyopengl ; extra == 'plato'
Provides-Extra: pyriodic
Requires-Dist: pyriodic-structures ; extra == 'pyriodic'
Provides-Extra: qt
Requires-Dist: qt.py ; extra == 'qt'
Requires-Dist: pyside2 ; extra == 'qt'
